soonq/__init__.py
soonq/broker.py
soonq/commands/__init__.py
soonq/commands/cli.py
soonq/commands/commands.py
soonq/commands/run_task.py
soonq/commands/start_worker.py
soonq/config.py
soonq/instance/queue.sqlite
soonq/task.py
soonq/utils.py
soonq/worker.py
soonq-0.4.1.dist-info/entry_points.txt
soonq-0.4.1.dist-info/LICENSE
soonq-0.4.1.dist-info/WHEEL
soonq-0.4.1.dist-info/METADATA
soonq-0.4.1.dist-info/RECORD
