Metadata-Version: 2.1
Name: soonq
Version: 0.4.1
Summary: Subprocess-based task queue.
Home-page: https://github.com/n8jhj/SoonQ
License: MIT
Keywords: subprocess,task,queue
Author: Nathaniel Jones
Author-email: nathaniel.j.jones@wsu.edu
Requires-Python: >=3.6,<4.0
Classifier: Development Status :: 1 - Planning
Classifier: Intended Audience :: Developers
Classifier: License :: OSI Approved :: MIT License
Classifier: Programming Language :: Python
Classifier: Programming Language :: Python :: 3
Classifier: Programming Language :: Python :: 3.6
Classifier: Programming Language :: Python :: 3.7
Classifier: Programming Language :: Python :: 3.8
Classifier: Programming Language :: Python :: 3.9
Classifier: Topic :: Utilities
Requires-Dist: click (>=7.0)
Requires-Dist: tabulate (>=0.8.9,<0.9.0)
Project-URL: Repository, https://github.com/n8jhj/SoonQ
